setup.cfg
setup.py
byteasm/__init__.py
byteasm/aexpr.py
byteasm/assemble.py
byteasm/builder.py
byteasm/constants.py
byteasm/stack.py
byteasm/utils.py
byteasm/visualization.py
byteasm/visutil.py
byteasm.egg-info/PKG-INFO
byteasm.egg-info/SOURCES.txt
byteasm.egg-info/dependency_links.txt
byteasm.egg-info/top_level.txt
test/test.py