Metadata-Version: 1.1
Name: byteasm
Version: 0.2
Summary: an assembler for python bytecode
Home-page: https://github.com/zachariahreed/byteasm
Author: Zachariah Reed
Author-email: zreed@fastmail.com
License: GPL
Download-URL: https://github.com/zachariahreed/byteasm/tarball/0.2
Platform: any
Classifier: Development Status :: 4 - Beta
Classifier: Intended Audience :: Developers
Classifier: License :: OSI Approved :: GNU General Public License v3 or later (GPLv3+)
Classifier: Programming Language :: Python :: 3 :: Only
Classifier: Programming Language :: Python :: 3.6
